{
  "node": [
    {
      "attr": {
        "dtype": {
          "type": "DT_FLOAT32"
        },
        "shape": {
          "shape": {
            "dim": [
              {
                "size": "-1"
              },
              {
                "size": "784"
              }
            ]
          }
        },
        "_output_shapes": {
          "list": {
            "shape": [
              {
                "dim": [
                  {
                    "size": "-1"
                  },
                  {
                    "size": "784"
                  }
                ]
              }
            ]
          }
        }
      },
      "name": "activation_1_input",
      "op": "DataInput"
    },
    {
      "attr": {
        "dtype": {
          "type": "DT_FLOAT32"
        },
        "_output_shapes": {
          "list": {
            "shape": [
              {
                "dim": [
                  {
                    "size": "-1"
                  },
                  {
                    "size": "784"
                  }
                ]
              }
            ]
          }
        }
      },
      "input": [
        "activation_1_input"
      ],
      "name": "activation_1",
      "op": "Relu"
    },
    {
      "attr": {
        "units": {
          "i": "10"
        },
        "use_bias": {
          "b": true
        },
        "_output_shapes": {
          "list": {
            "shape": [
              {
                "dim": [
                  {
                    "size": "-1"
                  },
                  {
                    "size": "10"
                  }
                ]
              }
            ]
          }
        }
      },
      "input": [
        "activation_1"
      ],
      "name": "dense_1",
      "op": "FullyConnected"
    }
  ]
}